{
	"generator_info": "Shape definitions generated with PhysicsEditor. Visit https://www.codeandweb.com/physicseditor",
	"archer2": {
		"type": "fromPhysicsEditor",
		"label": "archer2",
		"isStatic": false,
		"density": 0.1,
		"restitution": 0,
		"friction": 0.1,
		"frictionAir": 0.01,
		"frictionStatic": 0.5,
		"collisionFilter": {
			"group": 0,
			"category": 1,
			"mask": 1
		},
		"fixtures": [
			{
				"label": "archer2",
				"isSensor": false,
				"vertices": [
					[ { "x":55, "y":76 }, { "x":58, "y":75 }, { "x":59, "y":71 }, { "x":56, "y":73 } ],
					[ { "x":63, "y":43 }, { "x":58, "y":43 }, { "x":57, "y":46 }, { "x":64, "y":49 } ],
					[ { "x":73, "y":69 }, { "x":69, "y":65 }, { "x":68, "y":68 } ],
					[ { "x":70, "y":76 }, { "x":73, "y":76 }, { "x":70, "y":74 } ],
					[ { "x":53, "y":45 }, { "x":50, "y":48 }, { "x":50, "y":51 }, { "x":53, "y":53 }, { "x":64, "y":49 }, { "x":57, "y":46 } ],
					[ { "x":56, "y":73 }, { "x":59, "y":71 }, { "x":64, "y":49 }, { "x":53, "y":67 }, { "x":52, "y":70 } ],
					[ { "x":73, "y":37 }, { "x":67, "y":39 }, { "x":69, "y":41 } ],
					[ { "x":53, "y":53 }, { "x":53, "y":67 }, { "x":64, "y":49 } ],
					[ { "x":65, "y":72 }, { "x":66, "y":70 }, { "x":64, "y":49 }, { "x":59, "y":71 } ],
					[ { "x":73, "y":76 }, { "x":68, "y":68 }, { "x":66, "y":70 }, { "x":70, "y":74 } ],
					[ { "x":68, "y":68 }, { "x":69, "y":65 }, { "x":67, "y":51 }, { "x":64, "y":49 }, { "x":66, "y":70 } ],
					[ { "x":73, "y":44 }, { "x":69, "y":41 }, { "x":67, "y":51 }, { "x":69, "y":65 }, { "x":73, "y":62 }, { "x":75, "y":58 }, { "x":75, "y":48 } ],
					[ { "x":67, "y":39 }, { "x":67, "y":51 }, { "x":69, "y":41 } ]
				]
			}
		]
	},
	"arrow": {
		"type": "fromPhysicsEditor",
		"isStatic": false,
		"density": 0.8,
		"restitution": 0.1,
		"friction": 0.1,
		"frictionAir": 0.001,
		"frictionStatic": 0.5,
		"collisionFilter": {
			"group": 0,
			"category": 1,
			"mask": 255
		},
		"label": "arrow",
		"fixtures": [
			{
				"label": "arrow",
				"isSensor": false,
				"vertices": [
					[
						{
							"x": 95,
							"y": 38
						},
						{
							"x": 95,
							"y": 41
						},
						{
							"x": 74,
							"y": 41
						},
						{
							"x": 74,
							"y": 38
						}
					]
				]
			}
		]
	}
}
